tabx/__init__.py
tabx/custom.py
tabx/table.py
tabx/utils.py
tabx_py-0.2.0.post1.dist-info/METADATA
tabx_py-0.2.0.post1.dist-info/WHEEL
tabx_py-0.2.0.post1.dist-info/licenses/LICENSE
tabx_py-0.2.0.post1.dist-info/RECORD
