Metadata-Version: 2.4
Name: tabx-py
Version: 0.2.0.post1
Summary: tabx - compose LaTeX tables using booktabs in Python
Project-URL: Homepage, https://github.com/jsr-p/tabx
Project-URL: Documentation, https://jsr-p.github.io/tabx
Project-URL: Repository, https://github.com/jsr-p/tabx
Author-email: jsr-p <jsr-p@sodas.ku.dk>
License-Expression: MIT
License-File: LICENSE
Classifier: License :: OSI Approved :: MIT License
Classifier: Programming Language :: Python :: 3
Classifier: Programming Language :: Python :: 3.11
Classifier: Programming Language :: Python :: 3.12
Requires-Python: <3.12,>=3.11
